sye_todo_cli/__init__.py
sye_todo_cli/todo.py
sye_todo_cli/todo_manager.py
syetodocliapp-1.2.dist-info/METADATA
syetodocliapp-1.2.dist-info/WHEEL
syetodocliapp-1.2.dist-info/entry_points.txt
syetodocliapp-1.2.dist-info/top_level.txt
syetodocliapp-1.2.dist-info/RECORD
