Metadata-Version: 2.1
Name: syetodocliapp
Version: 1.2
Summary: CLI Todo app with add, list, remove functionality as of now
Home-page: https://github.com/srisaipasupuleti/sye_todo_cli.git
Author: Srisai Pasupuleti
Author-email: srisaichiyan24@gmail.com
License: UNKNOWN
Platform: UNKNOWN
Classifier: Operating System :: OS Independent
Requires-Python: >=3.0
Requires-Dist: click
